{
    
    "line1": {
       "pd": {
        "2022年": 68653,
        "2021年": 68284.75,
        "2020年": 66949.15,
        "2019年": 66384.34,
        "2018年": 65789.22,
        "2017年": 66160.73
       },
        "rd":{
          "2022年": 24432.8,
          "2021年": 23954,
          "2020年": 23492,
          "2019年": 21630,
          "2018年": 20664,
          "2017年": 19565
       }
    },
    "line2":{
        "2022年": 83039.88,
        "2021年": 78339.51,
        "2020年": 71748.23,
        "2019年": 66066.45,
        "2018年": 61452.6,
        "2017年": 58059.76
       },
    "pie":[
        {
          "年份": "2022年",
          "ca1": {
            "种植业": 172383.2,
            "肉类": 9227,
            "水产品": 6869
          },
          "ca2": {
            "谷物": 63324,
            "蔬菜": 78764.98,
            "其他种植": 30294.22,
            "猪肉产量": 5541,
            "牛肉产量": 718,
            "羊肉产量": 525,
            "其他肉类": 2443,
            "人工养殖": 5399.8,
            "天然养殖": 1469.2
          },
          "总和（万吨）": 188479.2
        },
        {
          "年份": "2021年",
          "ca1": {
            "种植业产量(万吨)": 170650.92,
            "肉类产量(万吨)": 8989.99,
            "水产品总产量(万吨)": 6690.29
          },
          "ca2": {
            "谷物产量(万吨)": 63275.69,
            "蔬菜产量(万吨)": 77548.78,
            "其他种植(万吨）": 29826.45,
            "猪肉产量(万吨)": 5295.93,
            "牛肉产量(万吨)": 697.51,
            "羊肉产量(万吨)": 514.08,
            "其他肉类（万吨）": 2482.47,
            "人工养殖（万吨）": 5394.41,
            "天然养殖（万吨）": 1295.88
          },
          "总和（万吨）": 186331.2
        },
        {
          "年份": "2020年",
          "ca1": {
            "种植业产量(万吨)": 165399.83,
            "肉类产量(万吨)": 7748.38,
            "水产品总产量(万吨)": 6549.02
          },
          "ca2": {
            "谷物产量(万吨)": 61674.28,
            "蔬菜产量(万吨)": 74912.9,
            "其他种植(万吨）": 28812.65,
            "肉类产量(万吨)": 7748.38,
            "猪肉产量(万吨)": 4113.33,
            "牛肉产量(万吨)": 672.45,
            "羊肉产量(万吨)": 492.31,
            "其他肉类（万吨）": 2470.29,
            "人工养殖（万吨）": 5224.2,
            "天然养殖（万吨）": 1324.82
          },
          "总和（万吨）": 179697.23
        },
        {
          "年份": "2019年",
          "ca1": {
            "种植业产量(万吨)": 161204.1,
            "肉类产量(万吨)": 7758.78,
            "水产品总产量(万吨)": 6480.36
          },
          "ca2": {
            "谷物产量(万吨)": 61369.73,
            "蔬菜产量(万吨)": 72102.6,
            "其他种植(万吨）": 27731.77,
            "猪肉产量(万吨)": 4255.31,
            "牛肉产量(万吨)": 667.28,
            "羊肉产量(万吨)": 487.52,
            "其他肉类（万吨）": 2348.67,
            "人工养殖（万吨）": 5079.07,
            "天然养殖（万吨）": 1401.29
          },
          "总和（万吨）": 175443.24
        },
        {
          "年份": "2018年",
          "ca1": {
            "种植业产量(万吨)": 158406.73,
            "肉类产量(万吨)": 8624.63,
            "水产品总产量(万吨)": 6457.66
          },
          "ca2": {
            "谷物产量(万吨)": 61003.58,
            "蔬菜产量(万吨)": 70346.72,
            "其他种植(万吨）": 27056.43,
            "猪肉产量(万吨)": 5403.74,
            "牛肉产量(万吨)": 644.06,
            "羊肉产量(万吨)": 475.07,
            "其他肉类（万吨）": 2101.76,
            "人工养殖（万吨）": 4991.06,
            "天然养殖（万吨）": 1466.6
          },
          "总和（万吨）": 173489.02
        },
        {
          "年份": "2017年",
          "ca1": {
            "种植业产量(万吨)": 156109.52,
            "肉类产量(万吨)": 8654.43,
            "水产品总产量(万吨)": 6445.33
          },
          "ca2": {
            "谷物产量(万吨)": 61520.54,
            "蔬菜产量(万吨)": 69192.68,
            "其他种植(万吨）": 25396.3,
            "猪肉产量(万吨)": 5451.8,
            "牛肉产量(万吨)": 634.62,
            "羊肉产量(万吨)": 471.07,
            "其他肉类（万吨）": 2096.94,
            "人工养殖（万吨）": 4905.99,
            "天然养殖（万吨）": 1539.34
          },
          "总和（万吨）": 171209.28
        }
      ]
}